LICENSE
README.rst
foreshadow/ColumnTransformerWrapper.py
foreshadow/__init__.py
foreshadow/base.py
foreshadow/cachemanager.py
foreshadow/concrete/__init__.py
foreshadow/concrete/externals.py
foreshadow/concrete/internals/__init__.py
foreshadow/concrete/internals/cleaners/__init__.py
foreshadow/concrete/internals/cleaners/base.py
foreshadow/concrete/internals/cleaners/customizable_base.py
foreshadow/concrete/internals/cleaners/datetimes.py
foreshadow/concrete/internals/cleaners/drop.py
foreshadow/concrete/internals/cleaners/financial_cleaner.py
foreshadow/concrete/internals/cleaners/json_flattener.py
foreshadow/concrete/internals/dropfeature.py
foreshadow/concrete/internals/dummyencoder.py
foreshadow/concrete/internals/fancyimpute.py
foreshadow/concrete/internals/financial.py
foreshadow/concrete/internals/htmlremover.py
foreshadow/concrete/internals/labelencoder.py
foreshadow/concrete/internals/nan_filler.py
foreshadow/concrete/internals/notransform.py
foreshadow/concrete/internals/tfidf.py
foreshadow/concrete/internals/tostring.py
foreshadow/concrete/internals/uncommonremover.py
foreshadow/config.py
foreshadow/console.py
foreshadow/estimators/__init__.py
foreshadow/estimators/auto.py
foreshadow/estimators/config.py
foreshadow/estimators/estimator_wrapper.py
foreshadow/exceptions.py
foreshadow/foreshadow.py
foreshadow/intents/__init__.py
foreshadow/intents/base.py
foreshadow/intents/categorical.py
foreshadow/intents/droppable.py
foreshadow/intents/intent_type.py
foreshadow/intents/numeric.py
foreshadow/intents/text.py
foreshadow/logging/gui.py
foreshadow/logging/logging.py
foreshadow/metrics.py
foreshadow/optimizers/__init__.py
foreshadow/optimizers/param_distribution.py
foreshadow/optimizers/param_mapping.py
foreshadow/optimizers/random_search.py
foreshadow/optimizers/tuner.py
foreshadow/preparer.py
foreshadow/smart/__init__.py
foreshadow/smart/all.py
foreshadow/smart/cleaner.py
foreshadow/smart/data_exporter.py
foreshadow/smart/feature_engineerer.py
foreshadow-1.0.1.dist-info/entry_points.txt
foreshadow-1.0.1.dist-info/LICENSE
foreshadow-1.0.1.dist-info/WHEEL
foreshadow-1.0.1.dist-info/METADATA
foreshadow-1.0.1.dist-info/RECORD
