Metadata-Version: 2.1
Name: foreshadow
Version: 1.0.1
Summary: Peer into the future of a data science project
Home-page: https://foreshadow.readthedocs.io
License: Apache-2.0
Keywords: feature,machine,learning,automl,foreshadow
Author: Adithya Balaji
Author-email: adithyabsk@gmail.com
Requires-Python: >=3.6,<4.0
Classifier: Development Status :: 2 - Pre-Alpha
Classifier: Intended Audience :: Developers
Classifier: Intended Audience :: Education
Classifier: Intended Audience :: Science/Research
Classifier: License :: OSI Approved :: Apache Software License
Classifier: Programming Language :: Python :: 3
Classifier: Programming Language :: Python :: 3.5
Classifier: Programming Language :: Python :: 3.6
Classifier: Programming Language :: Python :: 3.7
Classifier: Topic :: Scientific/Engineering :: Artificial Intelligence
Classifier: Topic :: Software Development :: Libraries
Classifier: Topic :: Software Development :: Libraries :: Python Modules
Provides-Extra: doc
Requires-Dist: TPOT (>=0.11.0,<0.12.0)
Requires-Dist: category-encoders (>=1.2.8,<2.0.0)
Requires-Dist: docutils (<0.15.1); extra == "doc"
Requires-Dist: fancyimpute (>=0.3.2,<0.4.0)
Requires-Dist: hyperopt (>=0.1.2,<0.2.0)
Requires-Dist: jsonpickle (>=1.2,<2.0)
Requires-Dist: marshmallow (>=2.19.5,<3.0.0)
Requires-Dist: numpy (>=1.16.4,<2.0.0)
Requires-Dist: pandas (>=0.25.0,<0.26.0)
Requires-Dist: patchy (>=1.5,<2.0)
Requires-Dist: pyyaml (>=5.1,<6.0)
Requires-Dist: scikit-learn (>=0.22.1,<0.23.0)
Requires-Dist: scipy (>=1.1.0,<2.0.0)
Requires-Dist: scs (<=2.1.0)
Requires-Dist: sphinx (>=1.7.6,<2.0.0); extra == "doc"
Requires-Dist: sphinx_rtd_theme (>=0.4.1,<0.5.0); extra == "doc"
Requires-Dist: sphinxcontrib-plantuml (>=0.16.1,<0.17.0); extra == "doc"
Requires-Dist: toml (>=0.10.0,<0.11.0)
Project-URL: Documentation, https://foreshadow.readthedocs.io
Project-URL: Repository, https://github.com/georgianpartners/foreshadow
